GW_GWS_LC
LICENSE
MANIFEST.in
README.md
setup.cfg
setup.py
asdfssf/__init__.py
asdfssf.egg-info/PKG-INFO
asdfssf.egg-info/SOURCES.txt
asdfssf.egg-info/dependency_links.txt
asdfssf.egg-info/top_level.txt
asdfssf.egg-info/zip-safe